AUTHORS
LICENSE
MANIFEST.in
README.md
picostk
picostk-django
pstk
setup.py
picostack/__init__.py
picostack/deamon_app.py
picostack/errors.py
picostack/local_override.py
picostack/logging_util.py
picostack/process_spawn.py
picostack/settings.py
picostack/socket_logger.py
picostack/textwrap_util.py
picostack/urls.py
picostack/vm_builder.py
picostack/vm_manager.py
picostack/wsgi.py
picostack.egg-info/PKG-INFO
picostack.egg-info/SOURCES.txt
picostack.egg-info/dependency_links.txt
picostack.egg-info/requires.txt
picostack.egg-info/top_level.txt
picostack/static/pstk.css
picostack/static/bower_components/bootstrap/.bower.json
picostack/static/bower_components/bootstrap/Gruntfile.js
picostack/static/bower_components/bootstrap/LICENSE
picostack/static/bower_components/bootstrap/README.md
picostack/static/bower_components/bootstrap/bower.json
picostack/static/bower_components/bootstrap/package.json
picostack/static/bower_components/bootstrap/dist/css/bootstrap-theme.css
picostack/static/bower_components/bootstrap/dist/css/bootstrap-theme.css.map
picostack/static/bower_components/bootstrap/dist/css/bootstrap-theme.min.css
picostack/static/bower_components/bootstrap/dist/css/bootstrap.css
picostack/static/bower_components/bootstrap/dist/css/bootstrap.css.map
picostack/static/bower_components/bootstrap/dist/css/bootstrap.min.css
picostack/static/bower_components/bootstrap/dist/fonts/glyphicons-halflings-regular.eot
picostack/static/bower_components/bootstrap/dist/fonts/glyphicons-halflings-regular.svg
picostack/static/bower_components/bootstrap/dist/fonts/glyphicons-halflings-regular.ttf
picostack/static/bower_components/bootstrap/dist/fonts/glyphicons-halflings-regular.woff
picostack/static/bower_components/bootstrap/dist/js/bootstrap.js
picostack/static/bower_components/bootstrap/dist/js/bootstrap.min.js
picostack/static/bower_components/bootstrap/fonts/glyphicons-halflings-regular.eot
picostack/static/bower_components/bootstrap/fonts/glyphicons-halflings-regular.svg
picostack/static/bower_components/bootstrap/fonts/glyphicons-halflings-regular.ttf
picostack/static/bower_components/bootstrap/fonts/glyphicons-halflings-regular.woff
