Metadata-Version: 1.1
Name: picostack
Version: 0.1.10
Summary: A super lightweight KVM virtualization manager
Home-page: https://github.com/ewiger/picostack
Author: Yauhen Yakimovich
Author-email: eugeny.yakimovitch@gmail.com
License: MIT
Download-URL: https://github.com/ewiger/picostack/tarball/master
Platform: UNKNOWN
Classifier: Topic :: Internet :: WWW/HTTP :: Dynamic Content
Classifier: Topic :: System :: Emulators
Classifier: Intended Audience :: Developers
Classifier: Intended Audience :: System Administrators
Classifier: Programming Language :: Python
Classifier: Programming Language :: Python :: 2.7
Classifier: Framework :: Django
Classifier: Development Status :: 4 - Beta
Classifier: Operating System :: POSIX :: Linux
